Metadata-Version: 2.1
Name: python-synology-hub
Version: 1.0.0
Summary: Python API for communication with Synology DSM - Homelab Utility Belt edition
Home-page: https://github.com/thiagocrepaldi/python-synology
License: MIT
Keywords: synology-dsm,synology
Author: Thiago Crepaldi (thiagocrepaldi)
Requires-Python: >=3.7.0,<4.0.0
Classifier: Development Status :: 5 - Production/Stable
Classifier: Intended Audience :: Developers
Classifier: License :: OSI Approved :: MIT License
Classifier: Operating System :: OS Independent
Classifier: Programming Language :: Python
Classifier: Programming Language :: Python :: 3
Classifier: Programming Language :: Python :: 3 :: Only
Classifier: Programming Language :: Python :: 3.7
Classifier: Programming Language :: Python :: 3.8
Classifier: Programming Language :: Python :: 3.9
Classifier: Topic :: Software Development :: Libraries
Requires-Dist: requests (>=2.24.0,<3.0.0)
Requires-Dist: urllib3 (>=1.25.10,<2.0.0)
Project-URL: Changelog, https://github.com/thiagocrepaldi/python-synology/releases
Project-URL: Documentation, https://python-synology-hub.readthedocs.io
Project-URL: Repository, https://github.com/thiagocrepaldi/python-synology
